{
  "refId": "ironcannon/knowledge-w83-starter-golden-path-unchanged",
  "sourceUrl": "https://ironcannon.dev/knowledge/w83/starter-golden-path-unchanged",
  "lastVerified": "2026-06-06",
  "title": "W83 starter-golden-path-unchanged",
  "provider": "ironcannon",
  "excerpt": "starter:golden-path still 12/12 after expansion waves",
  "embeddingHint": "ironcannon starter-golden-path-unchanged wave83 session-harvest-g34",
  "tags": [
    "wave83",
    "knowledge",
    "ironcannon",
    "session-harvest-g34"
  ]
}
